Mini_AMF-0.9.1.dist-info/DESCRIPTION.rst
Mini_AMF-0.9.1.dist-info/METADATA
Mini_AMF-0.9.1.dist-info/RECORD
Mini_AMF-0.9.1.dist-info/WHEEL
Mini_AMF-0.9.1.dist-info/metadata.json
Mini_AMF-0.9.1.dist-info/top_level.txt
Mini_AMF-0.9.1.dist-info/zip-safe
miniamf/__init__.py
miniamf/_version.py
miniamf/alias.py
miniamf/amf0.py
miniamf/amf3.py
miniamf/codec.py
miniamf/sol.py
miniamf/versions.py
miniamf/xml.py
miniamf/_accel/__init__.py
miniamf/adapters/__init__.py
miniamf/adapters/_array.py
miniamf/adapters/_collections.py
miniamf/adapters/_decimal.py
miniamf/adapters/_sets.py
miniamf/adapters/_weakref.py
miniamf/adapters/util.py
miniamf/util/__init__.py
miniamf/util/imports.py
miniamf/util/pure.py
