Metadata-Version: 2.0
Name: Mini-AMF
Version: 0.9.1
Summary: AMF serialization and deserialization support for Python
Home-page: https://github.com/zackw/mini-amf
Author: Zack Weinberg, The PyAMF Project
Author-email: zackw@panix.com
License: MIT License
Keywords: amf,amf0,amf3,actionscript,air,flash,flashplayer,bytearray,recordset,decoder,encoder,sharedobject,lso,sol
Platform: UNKNOWN
Classifier: Intended Audience :: Developers
Classifier: Intended Audience :: Information Technology
Classifier: License :: OSI Approved :: MIT License
Classifier: Natural Language :: English
Classifier: Operating System :: OS Independent
Classifier: Programming Language :: C
Classifier: Programming Language :: Python
Classifier: Programming Language :: Cython
Classifier: Programming Language :: Python :: 2.7
Classifier: Topic :: Internet :: WWW/HTTP :: WSGI :: Application
Classifier: Topic :: Software Development :: Libraries :: Python Modules
Classifier: Development Status :: 5 - Production/Stable
Requires-Dist: defusedxml
Requires-Dist: six
Provides-Extra: docs
Requires-Dist: sphinx (>=1.5); extra == 'docs'
